{
  "coffre": [
    {
      "format": "%d",
      "iter": [
        4
      ]
    }
  ],
  "grade": [
    {
      "format": "grade_%d",
      "iter": [ 15 ]
    }
  ],
  "objet": [
    {
      "format": "aile%d",
      "iter": [
        1
      ]
    },
    {
      "format": "aile_%d",
      "iter": [
        [3, 4, 5]
      ]
    },
    {
      "format": "barre_fer"
    },
    {
      "format": "bec_%d",
      "iter": [
        [2]
      ]
    },
    {
      "format": "blood"
    },
    {
      "format": "bolef5"
    },
    {
      "format": "bol_%02d",
      "iter": [ 2 ]
    },
    {
      "format": "boue%d",
      "iter": [ 1 ]
    },
    {
      "format": "bouteille_vide"
    },
    {
      "format": "cadavre_chenille"
    },
    {
      "format": "carapace"
    },
    {
      "format": "carapace%d",
      "iter": [
        2
      ]
    },
    {
      "format": "chapeau%d",
      "iter": [
        5
      ]
    },
    {
      "format": "clochette06yx7"
    },
    {
      "format": "coquille%d",
      "iter": [
        6
      ]
    },
    {
      "format": "crane"
    },
    {
      "format": "crane%d",
      "iter": [
        4
      ]
    },
    {
      "format": "criniere_herisson"
    },
    {
      "format": "cristal%d",
      "iter": [
        9
      ]
    },
    {
      "format": "cuir_depeceur"
    },
    {
      "format": "dent%d",
      "iter": [
        5
      ]
    },
    {
      "format": "defaut",
      "ext": ["gif"]
    },
    {
      "format": "feuille%d",
      "iter": [
        3
      ]
    },
    {
      "format": "fiolevide"
    },
    {
      "format": "fourrure"
    },
    {
      "format": "fourrure%d",
      "iter": [
        2
      ]
    },
    {
      "format": "fragment"
    },
    {
      "format": "grenat_poli"
    },
    {
      "format": "griffe"
    },
    {
      "format": "griffe%d",
      "iter": [
        2
      ]
    },
    {
      "format": "grimoire"
    },
    {
      "format": "lame_depeceur"
    },
    {
      "format": "manche_mineur"
    },
    {
      "format": "minerai%d",
      "iter": [
        11
      ]
    },
    {
      "format": "minerai_%s",
      "iter": [ ["fer", "argent"] ]
    },
    {
      "format": "minerai_cristal_rouge_%d",
      "iter": [
        1
      ]
    },
    {
      "format": "oeil"
    },
    {
      "format": "patte"
    },
    {
      "format": "peau_depeceur"
    },
    {
      "format": "peau%d",
      "iter": [
        6
      ]
    },
    {
      "format": "piece%d",
      "iter": [
        1
      ]
    },
    {
      "format": "pierre%d",
      "iter": [
        12
      ]
    },
    {
      "format": "pierre_golem"
    },
    {
      "format": "pierre_mineur"
    },
    {
      "format": "plume_coq"
    },
    {
      "format": "poudre%d",
      "iter": [ 10 ]
    },
    {
      "format": "queue%d",
      "iter": [
        6
      ]
    }
  ],
  "objetquete": [
    {
      "format": "jevx7i5doqbh"
    },
    {
      "format": "p9jp2wnq9bsa"
    },
    {
      "format": "zj20ek71lkzk"
    },
    {
      "format": "bousolle"
    },
    {
      "format": "branche%d",
      "iter": [
        1
      ]
    },
    {
      "format": "chardon"
    },
    {
      "format": "clef_%d",
      "iter": [
        [2, 3]
      ]
    },
    {
      "format": "cles_tresor"
    },
    {
      "format": "gateau_noel_%02d",
      "iter": [
        1
      ]
    },
    {
      "format": "parchemin%d",
      "iter": [
        5
      ]
    }
  ],
  "pancarte" : [
    {
      "format": "pillier_%s",
      "iter": [ ["bleu", "rouge"] ]
    },
    {
      "format": "charette%d",
      "iter": [ 2 ]
    },
    {
      "format": "moine%d",
      "iter": [ 4 ]
    },
    {
      "format": "pancarte%d",
      "iter": [ 3 ],
      "ext": [ "gif" ]
    },
    {
      "format": "rocher%d",
      "iter": [ 1 ]
    }
  ],
  "pnj": [
    {
      "format": "ambulant%d",
      "iter": [ 2 ]
    },
    {
      "format": "archalan"
    },
    {
      "format": "pnj%d",
      "iter": [ 96 ]
    },
    {
      "format": "pnj%d",
      "iter": [ [ 191, 192, 193, 549, 551, 666, 882, 883, 884, 885 ] ]
    },
    {
      "format": "pirate%d",
      "iter": [ 3 ]
    },
    {
      "format": "pilier"
    },
    {
      "format": "swirl%d",
      "iter": [
        20
      ]
    },
    {
      "format": "garde%d",
      "iter": [ 5 ]
    },
    {
      "format": "gardeTP%d",
      "iter": [ 3 ]
    },
    {
      "format": "statue1"
    },
    {
      "format": "paladin_varox"
    },
    {
      "format": "invisible",
      "ext": [ "gif" ]
    },
    {
      "format": "jeune_guerrier"
    },
    {
      "format": "Birduck"
    },
    {
      "format": "bougie"
    },
    {
      "format": "elfe"
    },
    {
      "format": "epee"
    },
    {
      "format": "herutis"
    },
    {
      "format": "Lhysern_Mc_Callum_Jr"
    },
    {
      "format": "lynus"
    },
    {
      "format": "Manashama"
    },
    {
      "format": "moine_copiste"
    },
    {
      "format": "tynus"
    },
    {
      "format": "pere_noel"
    },
    {
      "format": "pnj_tavernier"
    },
    {
      "format": "poulpe"
    },
    {
      "format": "Bamou"
    },
    {
      "format": "%s_%c",
      "iter": [
        [ "mort", "new_garde" ],
        ["r", "e", "c"]
      ]
    },
    {
      "name": "Divinités",
      "format": "%s",
      "iter": [["keirana", "randr", "joevina", "hardelbor", "burung", "heffquen", "maelic", "judbjorn" ]]
    }
  ],
  "pnjDetail": [
    {
      "format": "ambulant2_detail"
    },
    {
      "format": "archalan_detail"
    },
    {
      "format": "bougie"
    },
    {
      "format": "Bamou"
    },
    {
      "format": "Birduck"
    },
    {
      "format": "Combattant%02d",
      "iter": [ 1 ]
    },
    {
      "format": "competence"
    },
    {
      "format": "defaut"
    },
    {
      "format": "Eidola"
    },
    {
      "format": "elfe_detail"
    },
    {
      "format": "fille_couteau"
    },
    {
      "format": "garde%d_detail",
      "iter": [ 5 ]
    },
    {
      "format": "garde%d",
      "iter": [ 2 ]
    },
    {
      "format": "herutis"
    },
    {
      "format": "jeune_guerrier"
    },
    {
      "format": "lynus"
    },
    {
      "format": "Lhysern_Mc_Callum_Jr"
    },
    {
      "format": "Manashama"
    },
    {
      "format": "moine_copiste"
    },
    {
      "format": "paladin_varox"
    },
    {
      "format": "pere_noel"
    },
    {
      "format": "poulpe"
    },
    {
      "format": "pr_lactos"
    },
    {
      "format": "soldat_arene"
    },
    {
      "format": "tavernier"
    },
    {
      "format": "Tynus"
    },
    {
      "format": "pnj%ddetail",
      "iter": [ 95 ]
    },
    {
      "format": "pnj%d_detail",
      "iter": [ 94 ]
    },
    {
      "format": "pnj%ddetail",
      "iter": [ [191, 192, 193, 549, 551 ] ]
    },
    {
      "format": "pnj%d_detail",
      "iter": [ [666, 882, 883, 884, 885 ] ]
    },
    {
      "format": "pilier"
    },
    {
      "name": "Divinités",
      "format": "%s",
      "iter": [["keirana", "randr", "joevina", "hardelbor", "burung", "heffquen", "maelic", "judbjorn" ]]
    }
  ],
  "potion": [
    {
      "format": "boisson-gluante%d",
      "iter": [ 3 ]
    },
    {
      "format": "bonbec%d",
      "iter": [ 13 ]
    },
    {
      "format": "buffpot%d",
      "iter": [ 8 ]
    },
    {
      "format": "carotte"
    },
    {
      "format": "cheese"
    },
    {
      "format": "feuille%d",
      "iter": [ 11 ]
    },
    {
      "format": "flacon"
    },
    {
      "format": "gateau"
    },
    {
      "format": "gateauchamjaunekw8"
    },
    {
      "format": "millefeuilleschamsrz6"
    },
    {
      "format": "poisson%d",
      "iter": [ 5 ]
    },
    {
      "format": "pomme%d",
      "iter": [ 2 ]
    },
    {
      "format": "potion%d",
      "iter": [ 50 ]
    },
    {
      "format": "potion_mana%d",
      "iter": [ 3 ]
    },
    {
      "format": "potionrouge3D"
    },
    {
      "format": "potion_agile_majeure"
    },
    {
      "format": "potion_constit_majeure"
    },
    {
      "format": "potion_dext_majeure"
    },
    {
      "format": "potion_force_majeure"
    },
    {
      "format": "potiron"
    },
    {
      "format": "potmiel1uo7uc6"
    },
    {
      "format": "soupepoissonvapeuril7"
    },
    {
      "format": "soupepotironvapeurnu9"
    },
    {
      "format": "teteabeillemielrw5"
    },
    {
      "format": "tete_chenille",
      "ext": [ "jpg" ]
    },
    {
      "format": "viande%d",
      "iter": [ 7 ]
    }
  ],
  "competence": [
    {
      "format": "alchimiste_%d",
      "iter": [ 2 ]
    },
    {
      "format": "armurier_%d",
      "iter": [ 2 ]
    },
    {
      "format": "appel_sacre"
    },
    {
      "format": "blizzard"
    },
    {
      "format": "bouclier_divin"
    },
    {
      "format": "BSA"
    },
    {
      "format": "cassage_de_jambe"
    },
    {
      "format": "chasseur_de_prime"
    },
    {
      "format": "chatiment"
    },
    {
      "format": "coup_precis",
      "ext": [
        "gif"
      ]
    },
    {
      "format": "couturier_%d",
      "iter": [ 2 ]
    },
    {
      "format": "cogitation"
    },
    {
      "format": "cueillette"
    },
    {
      "format": "cuisinier_%d",
      "iter": [ 2 ]
    },
    {
      "format": "depecage"
    },
    {
      "format": "dephasage"
    },
    {
      "format": "esprit_voyageur",
      "ext": [
        "gif"
      ]
    },
    {
      "format": "esprit_voyageur_majeur",
      "ext": [
        "gif"
      ]
    },
    {
      "format": "exorcisme"
    },
    {
      "format": "felinite"
    },
    {
      "format": "filouterie"
    },
    {
      "format": "flute"
    },
    {
      "format": "forgeron_%d",
      "iter": [ 2 ]
    },
    {
      "format": "fracasse_crane"
    },
    {
      "format": "frappe_divine",
      "ext": [ "gif" ]
    },
    {
      "format": "frappe_sacree"
    },
    {
      "format": "frappe_supreme"
    },
    {
      "format": "furie"
    },
    {
      "format": "harpon_glace"
    },
    {
      "format": "intervention_divine"
    },
    {
      "format": "joaillier_%d",
      "iter": [ 2 ]
    },
    {
      "format": "justicier",
      "ext": [
        "gif"
      ]
    },
    {
      "format": "lien_tellurique"
    },
    {
      "format": "minage"
    },
    {
      "format": "miroir_glace"
    },
    {
      "format": "peche"
    },
    {
      "format": "piege_meurtrier"
    },
    {
      "format": "piege_mortel"
    },
    {
      "format": "pousser"
    },
    {
      "format": "projectile_magique"
    },
    {
      "format": "reflexes_accrus"
    },
    {
      "format": "regeneration_energie",
      "ext": [
        "gif"
      ]
    },
    {
      "format": "regeneration_vie",
      "ext": [
        "gif"
      ]
    },
    {
      "format": "secret_heros"
    },
    {
      "format": "skill%d",
      "iter": [
        124
      ],
      "ext": [
        "png",
        "gif"
      ]
    },
    {
      "format": "skill_RB"
    },
    {
      "format": "soin%d",
      "iter": [ 4 ]
    },
    {
      "format": "stalactite"
    },
    {
      "format": "suractivite_mineure",
      "ext": [
        "gif"
      ]
    },
    {
      "format": "tanneur_%d",
      "iter": [ 2 ]
    },
    {
      "format": "tempete"
    },
    {
      "format": "tirer"
    },
    {
      "format": "tir_precis",
      "ext": [ "gif" ]
    }
  ],
  "classe": [
    {
      "format": "manant_%c",
      "iter": [
        ["m", "f"]
      ]
    },
    {
      "format": "magicien_%s",
      "iter": [
        ["m", "mr", "me", "mc", "f", "fr", "fe", "fc"]
      ]
    },
    {
      "format": "moine_%s",
      "iter": [
        ["m", "mr", "me", "mc", "f", "fr", "fe", "fc"]
      ]
    },
    {
      "format": "guerrier_%s",
      "iter": [
        ["m", "mr", "me", "mc", "f", "fr", "fe", "fc"]
      ]
    },
    {
      "format": "archer_%s",
      "iter": [
        ["m", "mr", "me", "mc", "f", "fr", "fe", "fc"]
      ]
    },
    {
      "format": "franctireur_%s",
      "iter": [
        ["m", "mr", "me", "mc", "f", "fr", "fe", "fc"]
      ]
    },
    {
      "format": "druide_%s",
      "iter": [
        ["m", "mr", "me", "mc", "f", "fr", "fe", "fc"]
      ]
    },
    {
      "format": "barbare_%s",
      "iter": [
        ["m", "mr", "me", "mc", "f", "fr", "fe", "fc"]
      ]
    },
    {
      "format": "paladin_%s",
      "iter": [
        ["m", "mr", "me", "mc", "f", "fr", "fe", "fc"]
      ]
    },
    {
      "format": "pretre_%s",
      "iter": [
        ["m", "mr", "me", "mc", "f", "fr", "fe", "fc"]
      ]
    },
    {
      "format": "geomancien_%s",
      "iter": [
        ["m", "mr", "me", "mc", "f", "fr", "fe", "fc"]
      ]
    },
    {
      "format": "aquamancien_%s",
      "iter": [
        ["m", "mr", "me", "mc", "f", "fr", "fe", "fc"]
      ]
    },
    {
      "format": "heros_%s",
      "iter": [
        ["m", "mr", "me", "mc", "f", "fr", "fe", "fc"]
      ]
    },
    {
      "format": "heros_%s_%c",
      "iter": [
        ["m", "mr", "me", "mc", "f", "fr", "fe", "fc"],
        ["v", "f", "m", "c", "e"]
      ]
    },
    {
      "format": "bagnard%d",
      "iter": [
        2
      ]
    },
    {
      "format": "magicien_f",
      "ext": [
        "gif"
      ]
    },
    {
      "format": "balrog"
    },
    {
      "format": "felin",
      "ext": [ "gif" ]
    },
    {
      "format": "grenouille"
    },
    {
      "format": "ogre"
    },
    {
      "format": "druide_ours"
    },
    {
      "format": "metal"
    },
    {
      "format": "murdoc",
      "ext": [
        "gif"
      ]
    },
    {
      "format": "sparkman2",
      "ext": [
        "gif"
      ]
    },
    {
      "format": "diablo"
    },
    {
      "format": "muse"
    },
    {
      "format": "mort"
    },
    {
      "format": "fantome"
    },
    {
      "format": "fantome2"
    },
    {
      "format": "chauvesouris"
    },
    {
      "format": "chauve_souris2"
    },
    {
      "format": "vampire"
    },
    {
      "format": "golem"
    },
    {
      "format": "fillette"
    },
    {
      "format": "abeille"
    },
    {
      "format": "citrouille"
    },
    {
      "format": "blob"
    },
    {
      "format": "catapulte"
    },
    {
      "format": "pere_noel",
      "ext": [ "gif" ]
    }
  ],
  "ecran": [
    {
      "format": "auberge"
    }
  ],
  "primes": [
    {
      "format": "parchemin%d",
      "iter": [ 5 ]
    }
  ],
  "arme": [
    {
      "format": "amulette%02d",
      "iter": [
        13
      ]
    },
    {
      "format": "amuremort"
    },
    {
      "format": "anneaufer"
    },
    {
      "format": "anneauHallo"
    },
    {
      "format": "arbalete%d",
      "iter": [
        7
      ]
    },
    {
      "format": "arc%d",
      "iter": [
        16
      ]
    },
    {
      "format": "arc9_s"
    },
    {
      "format": "armemort"
    },
    {
      "format": "armure%d",
      "iter": [
        16
      ]
    },
    {
      "format": "badgeduconscrit%s",
      "iter": [ [ "rvk5", "cph4" ] ]
    },
    {
      "format": "bague%02d",
      "iter": [
        9
      ]
    },
    {
      "format": "bague%d",
      "iter": [
        17
      ]
    },
    {
      "format": "bague_bete_%s",
      "iter" : [ [ "puissante", "sup" ] ]
    },
    {
      "format": "bague_immortel"
    },
    {
      "format": "baguerouge01lt5"
    },
    {
      "format": "baguette%d",
      "iter": [
        4
      ]
    },
    {
      "format": "bas%d",
      "iter": [
        45
      ]
    },
    {
      "format": "bas%d_l",
      "iter": [
        [2, 8]
      ]
    },
    {
      "format": "bas_tempete_%s",
      "iter": [ ["scinti", "sup"] ]
    },
    {
      "format": "baton%d",
      "iter": [
        30
      ]
    },
    {
      "format": "baton_bete_puissant"
    },
    {
      "format": "baton_volcanos%s",
      "iter": [ [ "" , "_scinti"] ]
    },
    {
      "format": "beret"
    },
    {
      "format": "bonnet_noel%s",
      "iter": [
        ["", "2", "_new"]
      ]
    },
    {
      "format": "botte_justice_%s",
      "iter": [ ["leg", "sup"] ]
    },
    {
      "format": "botte_noel%s",
      "iter": [
        ["", "2", "_new"]
      ]
    },
    {
      "format": "bottes%d",
      "iter": [
        26
      ]
    },
    {
      "format": "bottes%02d",
      "iter": [
        8
      ]
    },
    {
      "format": "bottes07_l"
    },
    {
      "format": "bottes08_l"
    },
    {
      "format": "botte_sauvage_puiss"
    },
    {
      "format": "boucle%d",
      "iter": [
        10
      ]
    },
    {
      "format": "bouclier%d",
      "iter": [
        18
      ]
    },
    {
      "format": "bouclier14_l"
    },
    {
      "format": "bottes11_l"
    },
    {
      "format": "bottes14_l"
    },
    {
      "format": "cacheoreilles"
    },
    {
      "format": "canne_a_peche"
    },
    {
      "format": "cape%d",
      "iter": [
        8
      ]
    },
    {
      "format": "capenoel"
    },
    {
      "format": "cape_noel%s",
      "iter": [
        ["2", "_new"]
      ]
    },
    {
      "format": "capuche_chasseur_%s",
      "iter": [["puissant","sup"]]
    },
    {
      "format": "capucheti9"
    },
    {
      "format": "cas_consc"
    },
    {
      "format": "casque_de_justice_puissant"
    },
    {
      "format": "champi"
    },
    {
      "format": "chapeau%d",
      "iter": [
        28
      ]
    },
    {
      "format": "chapka%d",
      "iter": [
        10
      ]
    },
    {
      "format": "chaussons_volcano_%s",
      "iter": [["scintillant","sup"]]
    },
    {
      "format": "chaussure_chasseur_%s",
      "iter": [["puissant","sup"]]
    },
    {
      "format": "chaussures%d",
      "iter": [
        12
      ]
    },
    {
      "format": "chaussures7_l"
    },
    {
      "format": "chemise%d",
      "iter": [
        2
      ]
    },
    {
      "format": "citrouille"
    },
    {
      "format": "cle%d",
      "iter": [
        1
      ]
    },
    {
      "format": "collier01_%s",
      "iter": [
        ["a", "g", "m", "p"]
      ]
    },
    {
      "format": "collier%02d",
      "iter": [
        4
      ]
    },
    {
      "format": "collier_infini_%s",
      "iter": [["sup", "scintillant"]]
    },
    {
      "format": "colliermort"
    },
    {
      "format": "collier_zephyr"
    },
    {
      "format": "cor"
    },
    {
      "format": "couronne%d",
      "iter": [
        4
      ]
    },
    {
      "format": "coutea%d",
      "iter": [
        10
      ]
    },
    {
      "format": "couteau%02d",
      "iter": [
        1
      ]
    },
    {
      "format": "crane%d",
      "iter": [
        2
      ]
    },
    {
      "format": "croix"
    },
    {
      "format": "crosse%d",
      "iter": [
        5
      ]
    },
    {
      "format": "dague%d",
      "iter": [
        2
      ]
    },
    {
      "format": "defaut_torse"
    },
    {
      "format": "echarpeduperenoeleg5"
    },
    {
      "format": "epee%d",
      "iter": [
        22
      ]
    },
    {
      "format": "epee_justice_%s",
      "iter": [["sup","scin"]]
    },
    {
      "format": "equip%d",
      "iter": [
        61
      ]
    },
    {
      "format": "escarpins01id3"
    },
    {
      "format": "fronde%02d",
      "iter": [
        1
      ]
    },
    {
      "format": "gant%02d",
      "iter": [
        9
      ]
    },
    {
      "format": "gant%d",
      "iter": [
        10
      ]
    },
    {
      "format": "gants01gf6"
    },
    {
      "format": "griffe%d",
      "iter": [
        4
      ]
    },
    {
      "format": "griffe"
    },
    {
      "format": "grimoire%d",
      "iter": [
        6
      ]
    },
    {
      "format": "grimoiremort"
    },
    {
      "format": "hache%d",
      "iter": [
        11
      ]
    },
    {
      "format": "hache_sauvage_%s",
      "iter": [["pui","sup"]]
    },
    {
      "format": "hachette"
    },
    {
      "format": "haut%d",
      "iter": [
        30
      ]
    },
    {
      "format": "haut8_l"
    },
    {
      "format": "haut14_l"
    },
    {
      "format": "madail%d",
      "iter": [
        10
      ]
    },
    {
      "format": "marteau%d",
      "iter":  [
        10
      ]
    },
    {
      "format": "masque%02d",
      "iter": [
        2
      ]
    },
    {
      "format": "masque_nature_%s",
      "iter": [["sup","scintillant"]]
    },
    {
      "format": "masse%d",
      "iter": [
        8
      ]
    },
    {
      "format": "mitain%d",
      "iter": [
        10
      ]
    },
    {
      "format": "ombrelle01tq1"
    },
    {
      "format": "paire_pantoufle_%s",
      "iter": [["puissante", "sup"]]
    },
    {
      "format": "pdtfnv1c2vk5"
    },
    {
      "format": "pelle%d",
      "iter": [
        1
      ]
    },
    {
      "format": "pelle%02d",
      "iter": [
        2
      ]
    },
    {
      "format": "pendentif"
    },
    {
      "format": "pendentif%02d",
      "iter": [
        11
      ]
    },
    {
      "format": "pied%02d",
      "iter": [
        2
      ]
    },
    {
      "format": "pierre%d",
      "iter": [
        8
      ]
    },
    {
      "format": "pioche"
    },
    {
      "format": "pioche%02d",
      "iter": [
        2
      ]
    },
    {
      "format": "robebal2jd4"
    },
    {
      "format": "sabre%02d",
      "iter": [
        4
      ]
    },
    {
      "format": "sandales%d",
      "iter": [
        5
      ]
    },
    {
      "format": "serpe"
    },
    {
      "format": "teteabeillerouge"
    },
    {
      "format": "tetechauvesouris"
    },
    {
      "format": "tetereduite"
    },
    {
      "format": "tetine"
    },
    {
      "format": "tiare01qr5"
    },
    {
      "format": "toge_pelerin_%spuissant",
      "iter": [["puissant","sup"]]
    },
    {
      "format": "tunique_aventurier"
    },
    {
      "format": "20039517vg7",
      "ext": [
        "jpg"
      ]
    },
    {
      "format": "arf_consc",
      "ext": [
        "jpg"
      ]
    },
    {
      "format": "arm_consc",
      "ext": [
        "jpg"
      ]
    },
    {
      "format": "cons_pant",
      "ext": [
        "jpg"
      ]
    },
    {
      "format": "consc_bouc",
      "ext": [
        "jpg"
      ]
    }
  ],
  "map": [
    {
      "format": "1ioedfza"
    },
    {
      "name": "La salle du passé",
      "format": "q7sktyzmq1mexqqy"
    },
    {
      "format": "nedmor_chateau"
    },
    {
      "format": "interieur"
    },
    {
      "name": "Salle du trone",
      "format": "rcflo9j7pd"
    },
    {
      "name": "Chateau de Nedmor",
      "format": "yj1qp2tousah6pow"
    },
    {
      "name": "Salle des partisans du roy",
      "format": "x731ut9mgy"
    },
    {
      "format": "2dffqsjy"
    },
    {
      "name": "Forêt silencieuse de Broquir",
      "format": "2s4f6e1sdf51qaa"
    },
    {
      "name": "Forêt de Broquir (sud)",
      "format": "z87df4cd56z6641"
    },
    {
      "name": "Forêt profonde de Broquir",
      "format": "dg51v6q65f1e6ghjkl"
    },
    {
      "name": "Forêt dangereuse de Broquir",
      "format": "ss84231vd68eta84"
    },
    {
      "name": "Plaine verdoyante de Rhogan",
      "format" : "dghrdf3vb2sd26"
    },
    {
      "name": "Rhogan",
      "format" : "fsf51zefsqf1"
    },
    {
      "name": "Sous-bois de Rhogan",
      "format" : "dtg6rt2g6er2g"
    },
    {
      "name": "Sous-bois de Rhogan",
      "format" : "rgerg541e5g4"
    },
    {
      "name": "Forêt des bras cassés",
      "format" : "rqhysxvwuvcu"
    },
    {
      "name": "Forêt des bras cassés",
      "format" : "jht73vax9y"
    },
    {
      "name": "Forêt des bras cassés",
      "format" : "u1mz4qju75"
    },
    {
      "name": "Forêt des bras cassés",
      "format" : "pxc0qegg"
    },
    {
      "name": "Couloir sombre",
      "format" : "4m11v0qagoiceu"
    },
    {
      "name": "Corridor de Far",
      "format" : "dfgdbgsregqlmp112"
    },
    {
      "name": "Corniche déboisée",
      "format" : "sqdfxcvty2312fgr"
    },
    {
      "name": "Forêt sombre",
      "format" : "6re4hr54z"
    },
    {
      "name": "Brosems",
      "format" : "scxcvxcbhrturtujkolo"
    },
    {
      "name": "Brosems",
      "format" : "xcvxcvcbnvgjghjyikklpo"
    },
    {
      "name": "Forêt dévastée",
      "format" : "azrluioifggdbcdff"
    },
    {
      "name": "Forêt dévastée",
      "format" : "sdxccvfgrtftyezeznjh"
    },
    {
      "name": "Avant poste des justiciers",
      "format" : "cvfghnjkloi865"
    },
    {
      "name": "Poste de garde",
      "format" : "1alllezesdqs1"
    },
    {
      "name": "Guet de Khemor",
      "format" : "1alllezesdqs2"
    },
    {
      "name": "Auberge de Brosems",
      "format" : "ergsdfsdckxjbcvbor"
    },
    {
      "name": "Abords de Tuléa",
      "format" : "13zesdqs3"
    },
    {
      "name": "Port de Tuléa",
      "format" : "5lllezesd4"
    },
    {
      "name": "Centre de Tuléa",
      "format" : "9llleze5"
    },
    {
      "name": "Maison délabrée",
      "format" : "xcvxc4422365"
    },
    {
      "name": "Auberge de Tuléa",
      "format" : "dfsdf342354"
    },
    {
      "name": "Sous-sol",
      "format" : "vxcvxcvx14sfsf"
    },
    {
      "name": "Sous-sol",
      "format" : "fzef8ezr6sdf3sdf1"
    },
    {
      "name": "Forêt de Brosems",
      "format" : "sdfgxcxciopklmjkluyaz"
    },
    {
      "name": "Forêt de Brosems",
      "format" : "sdfgxcxciopklmjkluyaz2"
    },
    {
      "name": "Cimetière",
      "format" : "djildfcbjjdrzexcv"
    },
    {
      "format": "3xrpttdsa"
    },
    {
      "format": "4sdzezoid"
    },
	{
	"name": "Clairière de Nch",
	"format": "7a2ckjq5"
	},
    {
	"name": "Forêt sombre",
      "format": "cne8585sd"
    },
    {
	"name": "Forêt sombre",
      "format": "ezrgpok52k2"
    },
    {
      "format": "xc9zfl23w515s9f"
    },
    {
      "format": "sdgvnbkiuluoiuerte"
    },
    {
      "format": "zhhd7n43jqje8ce"
    },
    {
      "name": "Corridor de Far",
      "format": "vbxbcvbncvneiiii"
    },
    {
      "format": "wwwxxdzssxnklmpouyg"
    },
    {
      "format": "pekge8754zeaf"
    },
    {
      "format": "oijeeck"
    },
    {
      "format": "ghrimlong10yjzjb"
    },
    {
      "format": "ghrimlong11btfeu"
    },
    {
      "format": "couloirsombre%d",
      "iter": [ 3 ]
    },
    {
      "format": "villeN%02d",
      "iter": [ 5 ]
    },
    {
      "format": "villeM%02d",
      "iter": [ 5 ]
    },
    {
      "format": "villeB%02d",
      "iter": [ 5 ]
    },
    {
      "format": "foret%d",
      "iter": [ 19 ]
    },
    {
      "name": "Vallon de Far",
      "format": "foret__14"
    },
    {
      "name": "Cimetiere",
      "format": "cimetiere%d",
      "iter": [
        2
      ]
    },
    {
      "format": "douane"
    },
    {
	  "name": "Begharan",
      "format": "maptuto"
    },
    {
	  "name": "Cave de la Distillerie",
      "format": "sous_sol"
    },
    {
	  "name": "Distillerie de Gertrude",
      "format": "villetuto"
    }
  ],
  "monstre/alpha": [
	{
	"format": "ours3_alpha"
	},
	{
	"format": "renard_alpha"
	},
	{
	"format": "bouquetin_alpha"
	},
	{
	"format": "herisson_lion_alpha"
	},
	{
	"format": "rat_alpha"
	}
  ],
  "monstre/insecte": [
    {
      "format": "lezard"
    },
    {
      "format": "gecko%d",
      "iter": [
        2
      ]
    },
    {
      "format": "escargot%d",
      "iter": [
        3
      ]
    },
    {
      "format": "insecte%02d",
      "iter": [
        2
      ]
    },
    {
      "format": "fourmi%d",
      "iter": [
        2
      ]
    },
    {
      "format": "chenille%d",
      "iter": [
        3
      ]
    },
    {
      "format": "mouche%d",
      "iter": [
        2
      ]
    },
    {
      "format": "lezard%d",
      "iter": [
        5
      ]
    },
    {
      "format": "scarabe%d",
      "iter": [
        9
      ]
    },
    {
      "format": "cloporte%d",
      "iter": [
        2
      ]
    },
    {
      "format": "grenouille%d",
      "iter": [
        2
      ]
    },
    {
      "format": "araignee%d",
      "iter": [
        5
      ]
    },
    {
      "format": "abeille%d",
      "iter": [
        3
      ]
    },
    {
      "format": "abeille%02d",
      "iter": [
        1
      ]
    },
    {
      "format": "libellule%d",
      "iter": [
        4
      ]
    }
  ],
  "monstre/prison": [
    {
      "format": "poisson"
    },
    {
      "format": "prisonnier"
    }
  ],
  "monstre/bizarre": [
    {
      "format": "tortue"
    },
    {
      "format": "galahaad"
    },
    {
      "format": "epouvantail"
    },
    {
      "format": "MudGolem"
    },
    {
      "format": "fantome%d",
      "iter": [
        1
      ]
    },
    {
      "format": "elemental%d",
      "iter": [
        13
      ]
    },
    {
      "format": "ange%d",
      "iter": [
        2
      ]
    }
  ],
  "monstre/bestiaux": [
    {
      "format": "chat3nd2"
    },
    {
      "format": "chat1do2"
    },
    {
      "format": "renard"
    },
    {
      "format": "hog"
    },
    {
      "format": "wolf"
    },
    {
      "format": "lizardman"
    },
    {
      "format": "serpentmer"
    },
    {
      "format": "coq%d",
      "iter": [
        2
      ]
    },
    {
      "format": "serpent%d",
      "iter": [
        4
      ]
    },
    {
      "format": "poisson%d",
      "iter": [
        3
      ]
    },
    {
      "format": "goblin%d",
      "iter": [
        1
      ]
    },
    {
      "format": "demon%d",
      "iter": [
        1
      ]
    },
    {
      "format": "ours%d",
      "iter": [
        6
      ]
    },
    {
      "format": "loup%d",
      "iter": [
        8
      ]
    },
    {
      "format": "chauve_souris%d",
      "iter": [
        1
      ]
    },
    {
      "format": "rat"
    }
  ],
  "monstre/boss": [
    {
      "format": "poisson"
    },
    {
      "format": "herisson-lion"
    },
    {
      "format": "bouquetin"
    },
    {
      "format": "dragon"
    },
    {
      "format": "ombre_ailee"
    },
    {
      "format": "Gomina"
    },
    {
      "format": "fv1006"
    },
    {
      "format": "aigle"
    },
    {
      "format": "soldat"
    },
    {
      "format": "yeti"
    }
  ],
  "monstre/flore": [
    {
      "format": "tournesol%d",
      "iter": [
        2
      ]
    },
    {
      "format": "champignon%d",
      "iter": [
        4
      ]
    },
    {
      "format": "champignon%02d",
      "iter": [
        3
      ]
    },
    {
      "format": "plantecarnivore%d",
      "iter": [
        3
      ]
    },
    {
      "format": "arbre%d",
      "iter": [
        6
      ]
    }
  ]
}
